abstraction/__init__.py
abstraction/models.py
abstraction/selenium/__init__.py
abstraction/selenium/action.py
abstraction/selenium/handler.py
tests/Object_example1.py
tests/__init__.py
tests/test.py
abstraction_bnadeau-0.1.11.dist-info/LICENSE
abstraction_bnadeau-0.1.11.dist-info/METADATA
abstraction_bnadeau-0.1.11.dist-info/WHEEL
abstraction_bnadeau-0.1.11.dist-info/top_level.txt
abstraction_bnadeau-0.1.11.dist-info/RECORD
