Metadata-Version: 2.1
Name: abstraction-bnadeau
Version: 0.1.11
Summary: A small example package
Home-page: https://github.com/crispycret/abstraction
Author: Brandon Nadeau
Author-email: 
License: UNKNOWN
Platform: UNKNOWN
Classifier: Programming Language :: Python :: 3
Classifier: License :: OSI Approved :: MIT License
Classifier: Operating System :: OS Independent
Requires-Python: >=3.6
